huzzy_rabbit/__init__.py
huzzy_rabbit/rabbit_mq.py
huzzy_rabbit-0.1.8.dist-info/METADATA
huzzy_rabbit-0.1.8.dist-info/WHEEL
huzzy_rabbit-0.1.8.dist-info/top_level.txt
huzzy_rabbit-0.1.8.dist-info/RECORD
