Metadata-Version: 2.4
Name: huzzy-rabbit
Version: 0.1.8
Summary: Add your description here
Requires-Python: >=3.10
Requires-Dist: aio-pika>=9.5.7
